EURUSD_package/__init__.py
EURUSD_package/analyzeForecast.py
EURUSD_package/dataAnalyzer.py
EURUSD_package/dataLoader.py
EURUSD_package/dataVisualizer.py
EURUSD_package/main.py
eurusd_package-0.1.0.dist-info/licenses/LICENSE
eurusd_package-0.1.0.dist-info/METADATA
eurusd_package-0.1.0.dist-info/WHEEL
eurusd_package-0.1.0.dist-info/top_level.txt
eurusd_package-0.1.0.dist-info/RECORD
