Metadata-Version: 2.4
Name: EURUSD_package
Version: 0.1.0
Summary: A package for analyzing and visualizing EUR/USD forex data
Requires-Python: >=3.8
License-File: LICENSE
Requires-Dist: numpy
Requires-Dist: pandas
Requires-Dist: matplotlib
Requires-Dist: seaborn
Requires-Dist: jupyter
Requires-Dist: statsmodels
Requires-Dist: plotly
Requires-Dist: prophet
Dynamic: license-file
